{
  "version": "v3.0",
  "dataStorage":{
    "rollingDeleteThreshold": 10,
    "rollInterval": 10,
    "bagInterval": 10,
    "storagePaths": {
      "bagPath": "/data/dcp/data/bag/shadow/",
      "encPath": "/data/dcp/data/enc",
      "MaskedPath": "/data/dcp/data/masked"
    },
    "capacityMb": 102400,
    "requiredSpaceMb": 256
  },
  "dataProto":{
    "vin": "LFBGEV070LJD45885",
    "software_version": "rc3.0",
    "hardware_version": "rc3.0",
    "device": "device1",
    "device_id": "V-Box2103010456",
    "mqtt": {
      "broker": "emqx-dna-vehicle.perf.dftccloud.t.home:9881",
      "broker_ssl": "ssl://dna-emq-perfs.dfiov.com.cn:10006",
      "username": "dnaapp",
      "password": "D7f%dnD&63B",
      "upTopic": "/SHADOW/sd@LFBGEV070LJD45885/V-Box2103010456/terminal/up/request",
      "downTopic": "/SHADOW/sd@LFBGEV070LJD45885/tsp/down/response"
    }
  },
  "dataUpload": {
    "retryCount":3,
    "retryIntervalSec": 10,
    "uploadFileIntervalMs": 100,
    "uploadFileSliceIntervalMs": 100,
    "uploadFileSliceSizeMb": 50,
    "clientCertPath": "/data/dcp/caic/resource/pki/client_cc.pem",
    "clientKeyPath": "/data/dcp/caic/resource/pki/client_ck.pem",
    "caCertPath": "/data/dcp/caic/resource/pki/server_ca.pem",
    "publicKeyPath": "/data/dcp/caic/resource/pki/public_key.pem",
    "gateway": "dnaivigw-perfs.dfiov.com.cn",
    "fileRecordPath": "/data/dcp/data/bag/shadow/file_record.json",
    "filenameRegex": "(\\.(record|lz4|zip)$)",
    "uploadPaths": {
      "bagPath": "/data/dcp/data/bag/shadow",
      "encPath": "/data/dcp/data/enc",
      "MaskedPath": "/data/dcp/data/masked"
    }
  },
  "log":{
    "LOG_level":"info",
    "LOG_pattern":"%Y%m%d-%H%M%S",
    "LOG_path":"/tmp/shadow_mode/log/",
    "LOG_basename":"shadow_mode"
  },
  "debug":{
    "closeMqttSsl":false,
    "closeDataReporter":false,
    "closeDataStorage":false,
    "closeDataEnc":false,
    "closeDataUpload":false,
    "deleteFileAfterDataUpload":true,
    "closeLogUpload":true,
    "cloudtimeOutMs":1000
  }

}